{
  "tests": [
    {
      "name": "02",
      "setup": "export a; a=`pwsh -c \"Write-Output (Get-Date).DayOfYear\"`",
      "run": "pwsh 02.ps1;a=`pwsh -c \"Write-Output (Get-Date).DayOfYear\"`",
      "input": "",
      "output": "347",
      "comparison": "included",
      "timeout": 1,
      "points": 1
    },
    {
      "name": "03",
      "setup": "",
      "run": "a=`pwsh -c \"Test-Path sdfsdf.ps1\"`; echo $a; if [ \"$a\" = False ]; then exit 1; fi ; exit 1;",
      "input": "",
      "output": "",
      "comparison": "included",
      "timeout": 1,
      "points": 1
    }
  ]
}